{"OBImbalanceScalper": {"BTC": {"current_imbalance": 0.4969, "avg_imbalance": 0.4621, "entry_threshold": 0.3, "persistence_needed": 2, "samples_collected": 10, "in_position": false, "signal": "buy_pressure"}, "ETH": {"current_imbalance": 0.7767, "avg_imbalance": 0.7982, "entry_threshold": 0.3, "persistence_needed": 2, "samples_collected": 10, "in_position": false, "signal": "buy_pressure"}, "SOL": {"current_imbalance": 0.8099, "avg_imbalance": 0.7918, "entry_threshold": 0.3, "persistence_needed": 2, "samples_collected": 10, "in_position": false, "signal": "buy_pressure"}, "HYPE": {"current_imbalance": -0.1798, "avg_imbalance": -0.2544, "entry_threshold": 0.3, "persistence_needed": 2, "samples_collected": 10, "in_position": false, "signal": "neutral"}}, "MomentumLS": {"BTC": {"momentum_score": null, "raw_score": null, "r_15m": null, "r_1h": null, "r_4h": null, "in_longs": false, "in_shorts": false, "candidate_side": "none"}, "ETH": {"momentum_score": null, "raw_score": null, "r_15m": null, "r_1h": null, "r_4h": null, "in_longs": false, "in_shorts": false, "candidate_side": "none"}, "SOL": {"momentum_score": null, "raw_score": null, "r_15m": null, "r_1h": null, "r_4h": null, "in_longs": false, "in_shorts": false, "candidate_side": "none"}, "HYPE": {"momentum_score": null, "raw_score": null, "r_15m": null, "r_1h": null, "r_4h": null, "in_longs": false, "in_shorts": false, "candidate_side": "none"}, "AVAX": {"momentum_score": null, "raw_score": null, "r_15m": null, "r_1h": null, "r_4h": null, "in_longs": false, "in_shorts": false, "candidate_side": "none"}, "LINK": {"momentum_score": null, "raw_score": null, "r_15m": null, "r_1h": null, "r_4h": null, "in_longs": false, "in_shorts": false, "candidate_side": "none"}, "ARB": {"momentum_score": null, "raw_score": null, "r_15m": null, "r_1h": null, "r_4h": null, "in_longs": false, "in_shorts": false, "candidate_side": "none"}, "OP": {"momentum_score": null, "raw_score": null, "r_15m": null, "r_1h": null, "r_4h": null, "in_longs": false, "in_shorts": false, "candidate_side": "none"}, "AAVE": {"momentum_score": null, "raw_score": null, "r_15m": null, "r_1h": null, "r_4h": null, "in_longs": false, "in_shorts": false, "candidate_side": "none"}, "LTC": {"momentum_score": null, "raw_score": null, "r_15m": null, "r_1h": null, "r_4h": null, "in_longs": false, "in_shorts": false, "candidate_side": "none"}, "BCH": {"momentum_score": null, "raw_score": null, "r_15m": null, "r_1h": null, "r_4h": null, "in_longs": false, "in_shorts": false, "candidate_side": "none"}, "XRP": {"momentum_score": null, "raw_score": null, "r_15m": null, "r_1h": null, "r_4h": null, "in_longs": false, "in_shorts": false, "candidate_side": "none"}}, "BreakoutControlled": {"BTC": {"resistance": 77936.5, "current_close": 77866.5, "bo_pct": -0.08981670975730241, "volume_ratio": 19.998780641192237, "signal_active": false, "pending_entry": false}, "ETH": {"resistance": 2176.95, "current_close": 2174.75, "bo_pct": -0.10105882082729592, "volume_ratio": 29.35901508394664, "signal_active": false, "pending_entry": false}, "SOL": {"resistance": 86.2425, "current_close": 86.1555, "bo_pct": -0.10087833724672093, "volume_ratio": 7.101120326068497, "signal_active": false, "pending_entry": true}, "HYPE": {"resistance": 41.0045, "current_close": 40.8475, "bo_pct": -0.3828848053262534, "volume_ratio": 11.620216671750613, "signal_active": false, "pending_entry": false}, "AVAX": {"resistance": 9.29215, "current_close": 9.28585, "bo_pct": -0.06779916381030794, "volume_ratio": 21.348426836224952, "signal_active": false, "pending_entry": false}, "LINK": {"resistance": 9.64645, "current_close": 9.63235, "bo_pct": -0.14616776119711514, "volume_ratio": 11.390841281776083, "signal_active": false, "pending_entry": false}, "ARB": {"resistance": 0.11954999999999999, "current_close": 0.119385, "bo_pct": -0.13801756587200723, "volume_ratio": 14.867981259732325, "signal_active": false, "pending_entry": true}, "OP": {"resistance": 0.13326, "current_close": 0.133195, "bo_pct": -0.04877682725497654, "volume_ratio": 11.269943408965542, "signal_active": true, "pending_entry": true}, "AAVE": {"resistance": 89.2925, "current_close": 89.2195, "bo_pct": -0.08175378671221827, "volume_ratio": 25.010816136922173, "signal_active": false, "pending_entry": true}, "LTC": {"resistance": 56.117999999999995, "current_close": 56.0755, "bo_pct": -0.0757332763106256, "volume_ratio": 4.023946186832567, "signal_active": false, "pending_entry": true}, "BCH": {"resistance": 414.795, "current_close": 414.795, "bo_pct": 0.0, "volume_ratio": 15.983200826025792, "signal_active": true, "pending_entry": true}, "XRP": {"resistance": 1.41195, "current_close": 1.41155, "bo_pct": -0.028329615071352097, "volume_ratio": 22.43388124168535, "signal_active": false, "pending_entry": true}}, "DonchianTrend": {"BTC": {"bars_15m": 2, "bars_1h": 0, "donchian_upper": null, "donchian_mid": null, "donchian_lower": null, "ema_1h": null, "btc_ema_4h": null, "vol_sma_15m": null, "atr_15m": null, "has_position": false, "trailing_stop": null}, "ETH": {"bars_15m": 2, "bars_1h": 0, "donchian_upper": null, "donchian_mid": null, "donchian_lower": null, "ema_1h": null, "btc_ema_4h": null, "vol_sma_15m": null, "atr_15m": null, "has_position": false, "trailing_stop": null}, "SOL": {"bars_15m": 2, "bars_1h": 0, "donchian_upper": null, "donchian_mid": null, "donchian_lower": null, "ema_1h": null, "btc_ema_4h": null, "vol_sma_15m": null, "atr_15m": null, "has_position": false, "trailing_stop": null}, "HYPE": {"bars_15m": 2, "bars_1h": 0, "donchian_upper": null, "donchian_mid": null, "donchian_lower": null, "ema_1h": null, "btc_ema_4h": null, "vol_sma_15m": null, "atr_15m": null, "has_position": false, "trailing_stop": null}, "AVAX": {"bars_15m": 2, "bars_1h": 0, "donchian_upper": null, "donchian_mid": null, "donchian_lower": null, "ema_1h": null, "btc_ema_4h": null, "vol_sma_15m": null, "atr_15m": null, "has_position": false, "trailing_stop": null}, "LINK": {"bars_15m": 2, "bars_1h": 0, "donchian_upper": null, "donchian_mid": null, "donchian_lower": null, "ema_1h": null, "btc_ema_4h": null, "vol_sma_15m": null, "atr_15m": null, "has_position": false, "trailing_stop": null}, "ARB": {"bars_15m": 2, "bars_1h": 0, "donchian_upper": null, "donchian_mid": null, "donchian_lower": null, "ema_1h": null, "btc_ema_4h": null, "vol_sma_15m": null, "atr_15m": null, "has_position": false, "trailing_stop": null}, "OP": {"bars_15m": 2, "bars_1h": 0, "donchian_upper": null, "donchian_mid": null, "donchian_lower": null, "ema_1h": null, "btc_ema_4h": null, "vol_sma_15m": null, "atr_15m": null, "has_position": false, "trailing_stop": null}, "AAVE": {"bars_15m": 2, "bars_1h": 0, "donchian_upper": null, "donchian_mid": null, "donchian_lower": null, "ema_1h": null, "btc_ema_4h": null, "vol_sma_15m": null, "atr_15m": null, "has_position": false, "trailing_stop": null}, "XRP": {"bars_15m": 2, "bars_1h": 0, "donchian_upper": null, "donchian_mid": null, "donchian_lower": null, "ema_1h": null, "btc_ema_4h": null, "vol_sma_15m": null, "atr_15m": null, "has_position": false, "trailing_stop": null}}, "VolatilityRegimeBreakout": {"BTC": {"atr_bps": 2.82, "regime": "low", "donchian_high": 77936.5, "donchian_low": 77820.5, "last_close": 77866.5, "high_vol_threshold": 25.0, "low_vol_threshold": 8.0, "bars_collected": 19, "in_position": false}, "ETH": {"atr_bps": 4.34, "regime": "low", "donchian_high": 2176.95, "donchian_low": 2171.85, "last_close": 2174.75, "high_vol_threshold": 25.0, "low_vol_threshold": 8.0, "bars_collected": 19, "in_position": false}, "SOL": {"atr_bps": 5.06, "regime": "low", "donchian_high": 86.2425, "donchian_low": 86.0565, "last_close": 86.1555, "high_vol_threshold": 25.0, "low_vol_threshold": 8.0, "bars_collected": 19, "in_position": false}, "HYPE": {"atr_bps": 11.65, "regime": "mid", "donchian_high": 41.0285, "donchian_low": 40.7915, "last_close": 40.8475, "high_vol_threshold": 25.0, "low_vol_threshold": 8.0, "bars_collected": 19, "in_position": false}, "AVAX": {"atr_bps": 5.17, "regime": "low", "donchian_high": 9.29215, "donchian_low": 9.26345, "last_close": 9.28585, "high_vol_threshold": 25.0, "low_vol_threshold": 8.0, "bars_collected": 19, "in_position": false}, "LINK": {"atr_bps": 6.64, "regime": "low", "donchian_high": 9.64645, "donchian_low": 9.61835, "last_close": 9.63235, "high_vol_threshold": 25.0, "low_vol_threshold": 8.0, "bars_collected": 19, "in_position": false}, "ARB": {"atr_bps": 5.68, "regime": "low", "donchian_high": 0.11955, "donchian_low": 0.119195, "last_close": 0.119385, "high_vol_threshold": 25.0, "low_vol_threshold": 8.0, "bars_collected": 19, "in_position": false}, "OP": {"atr_bps": 6.41, "regime": "low", "donchian_high": 0.13326, "donchian_low": 0.132785, "last_close": 0.133195, "high_vol_threshold": 25.0, "low_vol_threshold": 8.0, "bars_collected": 19, "in_position": false}, "AAVE": {"atr_bps": 6.78, "regime": "low", "donchian_high": 89.2925, "donchian_low": 88.987, "last_close": 89.2195, "high_vol_threshold": 25.0, "low_vol_threshold": 8.0, "bars_collected": 19, "in_position": false}, "XRP": {"atr_bps": 5.44, "regime": "low", "donchian_high": 1.41195, "donchian_low": 1.40805, "last_close": 1.41155, "high_vol_threshold": 25.0, "low_vol_threshold": 8.0, "bars_collected": 19, "in_position": false}}, "RSIBollingerReversion": {"BTC": {"bars_15m": 2, "close": 77880.5, "bb_upper": null, "bb_mid": null, "bb_lower": null, "rsi": null, "zscore": null, "was_oversold": false, "has_position": false, "ema_1h": null}, "ETH": {"bars_15m": 2, "close": 2174.45, "bb_upper": null, "bb_mid": null, "bb_lower": null, "rsi": null, "zscore": null, "was_oversold": false, "has_position": false, "ema_1h": null}, "SOL": {"bars_15m": 2, "close": 86.1395, "bb_upper": null, "bb_mid": null, "bb_lower": null, "rsi": null, "zscore": null, "was_oversold": false, "has_position": false, "ema_1h": null}, "AVAX": {"bars_15m": 2, "close": 9.2807, "bb_upper": null, "bb_mid": null, "bb_lower": null, "rsi": null, "zscore": null, "was_oversold": false, "has_position": false, "ema_1h": null}, "HYPE": {"bars_15m": 2, "close": 40.8325, "bb_upper": null, "bb_mid": null, "bb_lower": null, "rsi": null, "zscore": null, "was_oversold": false, "has_position": false, "ema_1h": null}}, "S8EMS": {"BTC": {"hurst": 0.5621488919878357, "hurst_regime": "TREND_LOW", "har_rv_forecast": null, "har_ratio": null, "wavelet_alert": true, "has_position": false}, "ETH": {"hurst": 0.6447361390666576, "hurst_regime": "TREND_LOW", "har_rv_forecast": null, "har_ratio": null, "wavelet_alert": true, "has_position": false}, "SOL": {"hurst": 0.748424689103034, "hurst_regime": "TREND_HIGH", "har_rv_forecast": null, "har_ratio": null, "wavelet_alert": false, "has_position": false}}, "MeanReversionKalman": {"BTC": {"z_score": 0.4809041018229903, "kalman_fv": 77885.95425569086, "innovation_sigma": 1.1348298071795295, "samples": 300, "min_innovation_samples": 200, "trend_guard": false, "in_position": false}, "ETH": {"z_score": 0.15500768397049647, "kalman_fv": 2175.745891675739, "innovation_sigma": 0.026504003902485435, "samples": 300, "min_innovation_samples": 200, "trend_guard": false, "in_position": false}, "SOL": {"z_score": -0.5478710055676435, "kalman_fv": 86.23571874182738, "innovation_sigma": 0.0022245050659763744, "samples": 300, "min_innovation_samples": 200, "trend_guard": false, "in_position": false}}, "FundingArbitrage": {"BTC": {"funding_rate": -1.6683625e-06, "funding_smoothed": -1.6437015625e-06, "r_24h_pct": null}, "ETH": {"funding_rate": 1.5625e-06, "funding_smoothed": 1.5625e-06, "r_24h_pct": null}, "SOL": {"funding_rate": -3.0741125e-06, "funding_smoothed": -2.9483296875e-06, "r_24h_pct": null}, "HYPE": {"funding_rate": 1.5625e-06, "funding_smoothed": 1.5625e-06, "r_24h_pct": null}}, "RotationMomentum": {"BTC": {"bars_1h": 0, "momentum": null, "rank": null, "n_ranked": 0, "is_top_k": false, "is_bot_k": false, "has_position": false}, "ETH": {"bars_1h": 0, "momentum": null, "rank": null, "n_ranked": 0, "is_top_k": false, "is_bot_k": false, "has_position": false}, "SOL": {"bars_1h": 0, "momentum": null, "rank": null, "n_ranked": 0, "is_top_k": false, "is_bot_k": false, "has_position": false}, "HYPE": {"bars_1h": 0, "momentum": null, "rank": null, "n_ranked": 0, "is_top_k": false, "is_bot_k": false, "has_position": false}, "AVAX": {"bars_1h": 0, "momentum": null, "rank": null, "n_ranked": 0, "is_top_k": false, "is_bot_k": false, "has_position": false}}, "RelativeValue": {"BTC": {}, "ETH": {"pairs": {"ETH/BTC": {"bars_1h_a": 0, "bars_1h_b": 0, "beta": null, "alpha": null, "z_score": null, "correlation": null, "has_position": false, "hedge_required": true, "executable": false}}}, "SOL": {"pairs": {"SOL/ETH": {"bars_1h_a": 0, "bars_1h_b": 0, "beta": null, "alpha": null, "z_score": null, "correlation": null, "has_position": false, "hedge_required": true, "executable": false}}}}, "MetaAlpha": {"BTC": {"peer_votes": {"OBImbalanceScalper": 1, "AlphaPressureScalper": 0, "BookFlowDivergenceReversal": 0, "AbsorptionReversal": 0, "MomentumLS": 0, "BreakoutControlled": 0, "DonchianTrend": 0, "VolatilityRegimeBreakout": 0, "RSIBollingerReversion": 0, "S8EMS": 0, "MeanReversionKalman": 0, "FundingArbitrage": 0, "RotationMomentum": 0, "RelativeValue": 0, "SecondsResearch": 0, "FundingArbEnhanced": 0, "SpotPerpBasis": 0, "FundingCarryHedged": 0}, "net_score": 1, "min_agreement_score": 2, "quorum_reached": false, "direction": "NEUTRAL", "peers_registered": ["OBImbalanceScalper", "AlphaPressureScalper", "BookFlowDivergenceReversal", "AbsorptionReversal", "MomentumLS", "BreakoutControlled", "DonchianTrend", "VolatilityRegimeBreakout", "RSIBollingerReversion", "S8EMS", "MeanReversionKalman", "FundingArbitrage", "RotationMomentum", "RelativeValue", "SecondsResearch", "FundingArbEnhanced", "SpotPerpBasis", "FundingCarryHedged"], "no_peers": false, "in_position": false}, "ETH": {"peer_votes": {"OBImbalanceScalper": 1, "AlphaPressureScalper": 0, "BookFlowDivergenceReversal": 0, "AbsorptionReversal": 0, "MomentumLS": 0, "BreakoutControlled": 0, "DonchianTrend": 0, "VolatilityRegimeBreakout": 0, "RSIBollingerReversion": 0, "S8EMS": 0, "MeanReversionKalman": 0, "FundingArbitrage": 0, "RotationMomentum": 0, "RelativeValue": 0, "SecondsResearch": 0, "FundingArbEnhanced": 0, "SpotPerpBasis": 0, "FundingCarryHedged": 0}, "net_score": 1, "min_agreement_score": 2, "quorum_reached": false, "direction": "NEUTRAL", "peers_registered": ["OBImbalanceScalper", "AlphaPressureScalper", "BookFlowDivergenceReversal", "AbsorptionReversal", "MomentumLS", "BreakoutControlled", "DonchianTrend", "VolatilityRegimeBreakout", "RSIBollingerReversion", "S8EMS", "MeanReversionKalman", "FundingArbitrage", "RotationMomentum", "RelativeValue", "SecondsResearch", "FundingArbEnhanced", "SpotPerpBasis", "FundingCarryHedged"], "no_peers": false, "in_position": false}, "SOL": {"peer_votes": {"OBImbalanceScalper": 1, "AlphaPressureScalper": 0, "BookFlowDivergenceReversal": 0, "AbsorptionReversal": 0, "MomentumLS": 0, "BreakoutControlled": 0, "DonchianTrend": 0, "VolatilityRegimeBreakout": 0, "RSIBollingerReversion": 0, "S8EMS": 0, "MeanReversionKalman": 0, "FundingArbitrage": 0, "RotationMomentum": 0, "RelativeValue": 0, "SecondsResearch": 0, "FundingArbEnhanced": 0, "SpotPerpBasis": 0, "FundingCarryHedged": 0}, "net_score": 1, "min_agreement_score": 2, "quorum_reached": false, "direction": "NEUTRAL", "peers_registered": ["OBImbalanceScalper", "AlphaPressureScalper", "BookFlowDivergenceReversal", "AbsorptionReversal", "MomentumLS", "BreakoutControlled", "DonchianTrend", "VolatilityRegimeBreakout", "RSIBollingerReversion", "S8EMS", "MeanReversionKalman", "FundingArbitrage", "RotationMomentum", "RelativeValue", "SecondsResearch", "FundingArbEnhanced", "SpotPerpBasis", "FundingCarryHedged"], "no_peers": false, "in_position": false}}, "SpotPerpBasis": {"BTC": {"perp_mid": 77886.5, "spot_price": null, "basis_bps": null, "basis_status": "no_data", "spot_available": false, "spot_age_seconds": null, "spot_stale": false, "action_bias": "no_data", "in_position": false, "mode": "perp_only_basis_proxy"}, "ETH": {"perp_mid": 2175.75, "spot_price": null, "basis_bps": null, "basis_status": "no_data", "spot_available": false, "spot_age_seconds": null, "spot_stale": false, "action_bias": "no_data", "in_position": false, "mode": "perp_only_basis_proxy"}}, "FundingCarryHedged": {"BTC": {"funding_bps_per_hour": -0.0167, "funding_smoothed_bps": -0.0164, "expected_edge_bps": -7.433, "entry_threshold_bps": 0.5, "expected_hold_hours": 4.0, "action_bias": "neutral", "allow_unhedged_perp": false, "hedge_mode_available": false, "in_position": false}, "ETH": {"funding_bps_per_hour": 0.0156, "funding_smoothed_bps": 0.0156, "expected_edge_bps": -7.438, "entry_threshold_bps": 0.5, "expected_hold_hours": 4.0, "action_bias": "neutral", "allow_unhedged_perp": false, "hedge_mode_available": false, "in_position": false}}}